envxtract/__init__.py
envxtract/advanced_analysis.py
envxtract/basic_analysis.py
envxtract/nc_processor.py
envxtract/raster_extractor.py
envxtract-0.1.3.dist-info/METADATA
envxtract-0.1.3.dist-info/WHEEL
envxtract-0.1.3.dist-info/licenses/LICENSE
envxtract-0.1.3.dist-info/RECORD
